astrobase/__init__.py
astrobase/astrobase.conf
astrobase/astrokep.py
astrobase/astrotess.py
astrobase/awsutils.py
astrobase/coordutils.py
astrobase/emailutils.py
astrobase/gcputils.py
astrobase/imageutils.py
astrobase/lcdb.py
astrobase/lcmath.py
astrobase/magnitudes.py
astrobase/modtemplate.py
astrobase/plotbase.py
astrobase/timeutils.py
astrobase/checkplot/__init__.py
astrobase/checkplot/pkl.py
astrobase/checkplot/pkl_io.py
astrobase/checkplot/pkl_png.py
astrobase/checkplot/pkl_postproc.py
astrobase/checkplot/pkl_utils.py
astrobase/checkplot/pkl_xmatch.py
astrobase/checkplot/png.py
astrobase/cpserver/__init__.py
astrobase/cpserver/checkplot-viewer.html
astrobase/cpserver/checkplot-viewer.js
astrobase/cpserver/checkplotlist.py
astrobase/cpserver/checkplotserver.py
astrobase/cpserver/checkplotserver_cphandlers.py
astrobase/cpserver/checkplotserver_handlers.py
astrobase/cpserver/checkplotserver_standalone.py
astrobase/cpserver/checkplotserver_toolhandlers.py
astrobase/cpserver/cps-assets/DejaVuSans.ttf
astrobase/cpserver/cps-assets/cpbase.html
astrobase/cpserver/cps-assets/cpindex.html
astrobase/cpserver/cps-assets/cpserver.css
astrobase/cpserver/cps-assets/cpserver.js
astrobase/cpserver/cps-assets/mousetrap.min.js
astrobase/cpserver/cps-assets/no-tool-results.png
astrobase/cpserver/cps-assets/nolc-available.png
astrobase/data/checkplot-filelist.json
astrobase/data/checkplot-pickle-flist.json
astrobase/data/cps-projects.json
astrobase/data/tai-utc.dat
astrobase/data/lcformats/binned-hat.json
astrobase/data/lcformats/binned-hp.json
astrobase/data/lcformats/binned-kep.json
astrobase/data/lcformats/binned-tess.json
astrobase/data/lcformats/hat-csv.json
astrobase/data/lcformats/hat-sql.json
astrobase/data/lcformats/hp-pkl.json
astrobase/data/lcformats/hp-txt.json
astrobase/data/lcformats/kep-fits.json
astrobase/data/lcformats/kep-pkl.json
astrobase/data/lcformats/tess-fits.json
astrobase/data/lcformats/tess-pkl.json
astrobase/fakelcs/__init__.py
astrobase-0.5.3.dist-info/LICENSE
astrobase-0.5.3.dist-info/METADATA
astrobase-0.5.3.dist-info/WHEEL
astrobase-0.5.3.dist-info/entry_points.txt
astrobase-0.5.3.dist-info/top_level.txt
astrobase-0.5.3.dist-info/RECORD
