Metadata-Version: 2.1
Name: astrobase
Version: 0.5.3
Summary: Python modules and scripts useful for variable star work in astronomy.
Home-page: https://github.com/waqasbhatti/astrobase
Author: Waqas Bhatti
Author-email: waqas.afzal.bhatti@gmail.com
License: MIT
Keywords: astronomy
Platform: UNKNOWN
Classifier: Development Status :: 4 - Beta
Classifier: License :: OSI Approved :: MIT License
Classifier: Intended Audience :: Science/Research
Classifier: Topic :: Scientific/Engineering :: Astronomy
Classifier: Operating System :: OS Independent
Classifier: Programming Language :: Python :: 3 :: Only
Classifier: Programming Language :: Python :: 3
Classifier: Programming Language :: Python :: 3.5
Classifier: Programming Language :: Python :: 3.6
Classifier: Programming Language :: Python :: 3.7
Classifier: Programming Language :: Python :: 3.8
Requires-Python: >=3.5
Requires-Dist: numpy (>=1.4.0)
Requires-Dist: scipy (>=0.17.0)
Requires-Dist: astropy (>=1.3)
Requires-Dist: matplotlib (>=2.0)
Requires-Dist: Pillow
Requires-Dist: jplephem
Requires-Dist: requests (>=2.20)
Requires-Dist: tornado
Requires-Dist: pyeebls (>=0.1.6)
Requires-Dist: tqdm
Requires-Dist: scikit-learn (>=0.19)
Provides-Extra: all
Requires-Dist: psycopg2-binary ; extra == 'all'
Requires-Dist: emcee (==3.0rc1) ; extra == 'all'
Requires-Dist: h5py ; extra == 'all'
Requires-Dist: batman-package ; extra == 'all'
Requires-Dist: corner ; extra == 'all'
Requires-Dist: transitleastsquares (>=1.0) ; extra == 'all'
Requires-Dist: paramiko ; extra == 'all'
Requires-Dist: boto3 ; extra == 'all'
Requires-Dist: awscli ; extra == 'all'
Requires-Dist: google-api-python-client ; extra == 'all'
Requires-Dist: google-cloud-storage ; extra == 'all'
Requires-Dist: google-cloud-pubsub ; extra == 'all'
Provides-Extra: aws
Requires-Dist: paramiko ; extra == 'aws'
Requires-Dist: boto3 ; extra == 'aws'
Requires-Dist: awscli ; extra == 'aws'
Provides-Extra: gcp
Requires-Dist: paramiko ; extra == 'gcp'
Requires-Dist: google-api-python-client ; extra == 'gcp'
Requires-Dist: google-cloud-storage ; extra == 'gcp'
Requires-Dist: google-cloud-pubsub ; extra == 'gcp'
Provides-Extra: mandelagol
Requires-Dist: emcee (==3.0rc1) ; extra == 'mandelagol'
Requires-Dist: h5py ; extra == 'mandelagol'
Requires-Dist: batman-package ; extra == 'mandelagol'
Requires-Dist: corner ; extra == 'mandelagol'
Provides-Extra: tls
Requires-Dist: emcee (==3.0rc1) ; extra == 'tls'
Requires-Dist: h5py ; extra == 'tls'
Requires-Dist: batman-package ; extra == 'tls'
Requires-Dist: transitleastsquares (>=1.0) ; extra == 'tls'
Requires-Dist: corner ; extra == 'tls'
